safeagent/__init__.py
safeagent/config.py
safeagent/embeddings.py
safeagent/governance.py
safeagent/llm_client.py
safeagent/memory_manager.py
safeagent/orchestrator.py
safeagent/pipeline.py
safeagent/prompt_renderer.py
safeagent/protocol_manager.py
safeagent/retriever.py
safeagent/sinks.py
safeagent/stateful_orchestrator.py
safeagent/tool_registry.py
safeagent/utils.py
safeagent-0.1.3.dist-info/licenses/LICENSE
safeagent-0.1.3.dist-info/METADATA
safeagent-0.1.3.dist-info/WHEEL
safeagent-0.1.3.dist-info/top_level.txt
safeagent-0.1.3.dist-info/RECORD
