Metadata-Version: 2.4
Name: safeagent
Version: 0.1.3
Summary: A minimal and flexible framework for orchestrating LLM workflows.
Author: Viktor Veselov
License: MIT License
Classifier: Programming Language :: Python :: 3
Classifier: License :: OSI Approved :: MIT License
Classifier: Operating System :: OS Independent
Requires-Python: >=3.8
License-File: LICENSE
Requires-Dist: requests
Requires-Dist: jinja2
Requires-Dist: py-rbac
Requires-Dist: faiss-cpu
Requires-Dist: neo4j
Requires-Dist: redis
Requires-Dist: numpy
Requires-Dist: cryptography
Provides-Extra: test
Requires-Dist: pytest; extra == "test"
Dynamic: license-file
